dataproc_spark_connect-1.0.1.dist-info/licenses/LICENSE
google/cloud/dataproc_spark_connect/__init__.py
google/cloud/dataproc_spark_connect/environment.py
google/cloud/dataproc_spark_connect/exceptions.py
google/cloud/dataproc_spark_connect/pypi_artifacts.py
google/cloud/dataproc_spark_connect/session.py
google/cloud/dataproc_spark_connect/client/__init__.py
google/cloud/dataproc_spark_connect/client/core.py
google/cloud/dataproc_spark_connect/client/proxy.py
dataproc_spark_connect-1.0.1.dist-info/METADATA
dataproc_spark_connect-1.0.1.dist-info/WHEEL
dataproc_spark_connect-1.0.1.dist-info/top_level.txt
dataproc_spark_connect-1.0.1.dist-info/RECORD
