Metadata-Version: 2.4
Name: dataproc-spark-connect
Version: 1.0.1
Summary: Dataproc client library for Spark Connect
Home-page: https://github.com/GoogleCloudDataproc/dataproc-spark-connect-python
Author: Google LLC
License: Apache 2.0
License-File: LICENSE
Requires-Dist: google-api-core>=2.19
Requires-Dist: google-cloud-dataproc>=5.18
Requires-Dist: packaging>=20.0
Requires-Dist: pyspark[connect]~=4.0.0
Requires-Dist: tqdm>=4.67
Requires-Dist: websockets>=14.0
Dynamic: author
Dynamic: description
Dynamic: home-page
Dynamic: license
Dynamic: license-file
Dynamic: requires-dist
Dynamic: summary
